README
setup.py
httputils/__init__.py
httputils/httputils.py
httputils.egg-info/PKG-INFO
httputils.egg-info/SOURCES.txt
httputils.egg-info/dependency_links.txt
httputils.egg-info/top_level.txt