Metadata-Version: 1.0
Name: httputils
Version: 0.1b
Summary: Simple python library used to wrap httplib function
Home-page: http://packages.python.org/httputils
Author: Rizky Abdilah
Author-email: rizky.abdilah.mail@gmail.com
License: GPL
Keywords: httputils,httplib
Platform: UNKNOWN
Classifier: Development Status :: 4 - Beta
Classifier: Topic :: Utilities
Classifier: License :: OSI Approved :: GNU General Public License (GPL)
